chatgpt_memory/__init__.py
chatgpt_memory/constants.py
chatgpt_memory/datastore/__init__.py
chatgpt_memory/datastore/config.py
chatgpt_memory/datastore/datastore.py
chatgpt_memory/datastore/redis.py
chatgpt_memory/environment.py
chatgpt_memory/errors.py
chatgpt_memory/llm_client/__init__.py
chatgpt_memory/llm_client/config.py
chatgpt_memory/llm_client/llm_client.py
chatgpt_memory/llm_client/openai/__init__.py
chatgpt_memory/llm_client/openai/conversation/__init__.py
chatgpt_memory/llm_client/openai/conversation/chatgpt_client.py
chatgpt_memory/llm_client/openai/conversation/config.py
chatgpt_memory/llm_client/openai/embedding/__init__.py
chatgpt_memory/llm_client/openai/embedding/config.py
chatgpt_memory/llm_client/openai/embedding/embedding_client.py
chatgpt_memory/memory/__init__.py
chatgpt_memory/memory/manager.py
chatgpt_memory/memory/memory.py
chatgpt_memory/utils/openai_utils.py
chatgpt_memory/utils/reflection.py
chatgpt_memory-0.0.1.dist-info/LICENSE
chatgpt_memory-0.0.1.dist-info/METADATA
chatgpt_memory-0.0.1.dist-info/WHEEL
chatgpt_memory-0.0.1.dist-info/RECORD
