Metadata-Version: 2.1
Name: chatgpt-memory
Version: 0.0.1
Summary: 
Author: Shahrukh Khan
Requires-Python: >=3.10,<4.0
Classifier: Programming Language :: Python :: 3
Classifier: Programming Language :: Python :: 3.10
Classifier: Programming Language :: Python :: 3.11
Requires-Dist: langchain (>=0.0.113,<0.0.114)
Requires-Dist: numpy (>=1.24.2,<2.0.0)
Requires-Dist: openai (>=0.27.2,<0.28.0)
Requires-Dist: pydantic (>=1.10.0,<2.0.0)
Requires-Dist: pytest (>=7.2.2,<8.0.0)
Requires-Dist: redis (>=4.5.1,<5.0.0)
Requires-Dist: requests (>=2.28.2,<3.0.0)
Requires-Dist: tqdm (>=4.65.0,<5.0.0)
Requires-Dist: transformers (>=4.26.1,<5.0.0)
